{
  "num": 41,
  "order": 0,
  "indType": 0,
  "age": 0,
  "pitchType": 0,
  "underwater": 0,
  "joystick": 0,
  "blocks": [
    {
      "condition": "Control",
      "expData": []
    },
    {
      "condition": "Control",
      "expData": [
        {
          "trial": 2,
          "startAttitude": {
            "pitch": 0.0,
            "roll": 0.0
          },
          "finalAttitude": {
            "pitch": 0.0,
            "roll": 353.5933
          },
          "trialCondition": 0,
          "trialTime": 1.45112419
        },
        {
          "trial": 2,
          "startAttitude": {
            "pitch": 0.0,
            "roll": 0.0
          },
          "finalAttitude": {
            "pitch": 6.89147758,
            "roll": 5.455232
          },
          "trialCondition": 0,
          "trialTime": 1.5184288
        }
      ]
    },
    {
      "condition": "PseudoHaptic",
      "expData": []
    },
    {
      "condition": "PseudoHaptic",
      "expData": [
        {
          "trial": 2,
          "startAttitude": {
            "pitch": 0.0,
            "roll": 0.0
          },
          "finalAttitude": {
            "pitch": 0.0,
            "roll": 353.5933
          },
          "trialCondition": 0,
          "trialTime": 1.45112419
        },
        {
          "trial": 2,
          "startAttitude": {
            "pitch": 0.0,
            "roll": 0.0
          },
          "finalAttitude": {
            "pitch": 6.89147758,
            "roll": 5.455232
          },
          "trialCondition": 0,
          "trialTime": 1.5184288
        }
      ]
    }
  ],
  "gender": "Male"
}